{
    "idea":"中心となるアイデア",
    "children":[
        {
            "idea":"アイデア1",
            "children":[
                {"idea":"アイデア1_A"},
                {"idea":"アイデア1_B"},
                {"idea":"アイデア1_C"}
            ]
        },
        {
            "idea":"アイデア2",
            "children":[
                {"idea":"アイデア2_A"},
                {"idea":"アイデア2_B"}              
            ]
        },
        {
            "idea":"アイデア3",
            "children":[
                {"idea":"アイデア3_A"},
                {"idea":"アイデア3_B"}        
            ]
        }
    ]
}